{"commitInfo":{"timestamp":1753168386774,"operation":"WRITE","operationParameters":{"mode":"Append","partitionBy":"[]"},"readVersion":13,"isolationLevel":"Serializable","isBlindAppend":true,"operationMetrics":{"numFiles":"3","numOutputRows":"2","numOutputBytes":"1877"},"engineInfo":"Apache-Spark/4.0.0 Delta-Lake/4.0.0","txnId":"87107076-0ab7-4a23-8404-4fdd79cb6749"}}
{"add":{"path":"part-00003-09cd6e2f-3ecd-4296-9493-498d3d7320e4-c000.snappy.parquet","partitionValues":{},"size":756,"modificationTime":1753168386647,"dataChange":true,"stats":"{\"numRecords\":1,\"minValues\":{\"id\":4,\"name\":\"DAvid\"},\"maxValues\":{\"id\":4,\"name\":\"DAvid\"},\"nullCount\":{\"id\":0,\"name\":0}}"}}
{"add":{"path":"part-00007-8d660754-787d-4e2e-a53e-dd8c70f19715-c000.snappy.parquet","partitionValues":{},"size":742,"modificationTime":1753168386656,"dataChange":true,"stats":"{\"numRecords\":1,\"minValues\":{\"id\":5,\"name\":\"Eva\"},\"maxValues\":{\"id\":5,\"name\":\"Eva\"},\"nullCount\":{\"id\":0,\"name\":0}}"}}
